magic8ballfortunes/__init__.py
magic8ballfortunes/__main__.py
magic8ballfortunes/data.json
magic8ballfortunes/fortunes.py
magic8ballfortunes-0.0.9.dist-info/licenses/LICENSE
magic8ballfortunes-0.0.9.dist-info/METADATA
magic8ballfortunes-0.0.9.dist-info/WHEEL
magic8ballfortunes-0.0.9.dist-info/entry_points.txt
magic8ballfortunes-0.0.9.dist-info/top_level.txt
magic8ballfortunes-0.0.9.dist-info/RECORD
