Metadata-Version: 2.4
Name: magic8ballfortunes
Version: 0.0.9
Summary: An example of a package developed with pipenv, built with build using setuptools, uploaded to PyPI using twine, and distributed via pip.
Author: Team Package
License:                     GNU GENERAL PUBLIC LICENSE
Project-URL: Homepage, https://github.com/software-students-spring2025/3-python-package-package
Project-URL: Repository, https://github.com/software-students-spring2025/3-python-package-package.git
Project-URL: Bug Tracker, https://github.com/software-students-spring2025/3-python-package-package/issues
Keywords: python,package,build,tutorial
Classifier: Programming Language :: Python :: 3
Classifier: Intended Audience :: Education
Classifier: License :: OSI Approved :: GNU General Public License v3 (GPLv3)
Classifier: Operating System :: OS Independent
Requires-Python: >=3.7
License-File: LICENSE
Provides-Extra: dev
Requires-Dist: pytest; extra == "dev"
Requires-Dist: build; extra == "dev"
Dynamic: license-file
